setup.cfg
setup.py
codigo_avulso_test_tutorial/__init__.py
codigo_avulso_test_tutorial/circulo.py
codigo_avulso_test_tutorial/figura_geometrica.py
codigo_avulso_test_tutorial/quadrado.py
codigo_avulso_test_tutorial.egg-info/PKG-INFO
codigo_avulso_test_tutorial.egg-info/SOURCES.txt
codigo_avulso_test_tutorial.egg-info/dependency_links.txt
codigo_avulso_test_tutorial.egg-info/top_level.txt
test/__init__.py
test/circulo_test.py
test/figura_geometrica_test.py
test/quadrado_test.py